context42/README.md
context42/__init__.py
context42/chunker.py
context42/cli.py
context42/processor.py
context42/search.py
context42/server.py
context42/clara/__init__.py
context42/clara/config.py
context42/clara/generator.py
context42/clara/manager.py
context42-0.3.2.dist-info/METADATA
context42-0.3.2.dist-info/WHEEL
context42-0.3.2.dist-info/entry_points.txt
context42-0.3.2.dist-info/licenses/LICENSE
context42-0.3.2.dist-info/RECORD
