Metadata-Version: 2.4
Name: context42
Version: 0.3.2
Summary: MCP RAG Server with CLaRa semantic compression
Author-email: Aleksandr Beshkenadze <beshkenadze@gmail.com>
License-File: LICENSE
Requires-Python: >=3.10
Requires-Dist: accelerate>=0.20.0
Requires-Dist: fastmcp>=2.0.0
Requires-Dist: huggingface-hub>=0.20.0
Requires-Dist: peft>=0.10.0
Requires-Dist: torch>=2.0.0
Requires-Dist: transformers>=4.20.0
Provides-Extra: all
Requires-Dist: pytest>=7.0.0; extra == 'all'
Provides-Extra: dev
Requires-Dist: pytest>=7.0.0; extra == 'dev'
Provides-Extra: lite
